Workbook

Sheet README
A1: HOME LOAN PREPAYMENT PLANNER
A3: WHAT THIS DOES — answers: if I pay extra in the early years, how many years and
A4: how much interest do I save, and which of my two loans should I attack first?
A6: HOW TO USE:
A7: 1. Inputs tab — set each loan's outstanding, rate, tenure, start date (yellow cells).
A8: The EMI is computed automatically.
A9: 2. Schedule_A / Schedule_B — to test a prepayment, type the extra amount in the
A10: yellow PREPAY column next to the month you'd pay it. The 'Rule check' column
A11: warns if it breaks an HDFC rule. The loan shortens automatically (tenure reduction).
A12: 3. Summary tab — see baseline vs your plan: interest saved, months/years saved,
A13: new payoff date, and which loan to prepay first.
A14: 4. Windfall What-If — got a one-time lump sum? Enter the amount + month and it tells
... A21: Yellow = you edit. Green = headline result. All numbers recalculate live in Excel.

Sheet Inputs
A1: INPUTS — edit the yellow cells
B2: Loan A | C2: Loan B
A3: Outstanding principal (Rs) | B3: 3500000 | C3: 5000000
A4: Annual interest rate (%) | B4: 7.25 | C4: 7.5
A5: Tenure (months) | B5: 180 | C5: 180
A6: Full-EMI start date | B6: 46204 | C6: 46204
A7: Monthly EMI (auto) | B7: =ROUNDUP(B3*(B4/100/12)*POWER(1+B4/100/12,B5)/(POWER(1+B4/100/12,B5)-1),0) | C7: =ROUNDUP(C3*(C4/100/12)*POWER(1+C4/100/12,C5)/(POWER(1+C4/100/12,C5)-1),0)
A8: Monthly rate (auto) | B8: =B4/100/12 | C8: =C4/100/12
A9: Pre-EMI interest (one-time) | B9: 17877 | C9: 0

Sheet Schedule_A
A1: AMORTIZATION SCHEDULE — Loan A | D1: (C-G: baseline, no prepayment | H: type any extra payment | J-P: your plan)
A2: Month | B2: Date | C2: Opening | D2: Interest | E2: EMI | F2: Principal | G2: Closing | H2: PREPAY (edit) | I2: Rule check | J2: Opening | K2: Interest | L2: EMI | M2: Principal | N2: Prepay | O2: Closing
A3: 1 | B3: =EDATE(Inputs!$B$6,A3-1) | C3: =Inputs!$B$3 | D3: =IF(C3<=0.005,0,ROUND(C3*Inputs!$B$8,2)) | E3: =IF(C3<=0.005,0,MIN(Inputs!$B$7,C3+D3)) | F3: =E3-D3 | G3: =ROUND(C3-F3,2) | H3: 0 | I3: =IF(H3=0,"",IF(A3<2,"X not before month 2",IF(H3<MAX(5000,Inputs!$B$7),"X below min",IF(H3>MIN(5000000,0.75*J3),"X above max","OK")))) | J3: =Inputs!$B$3 | K3: =IF(J3<=0.005,0,ROUND(J3*Inputs!$B$8,2)) | L3: =IF(J3<=0.005,0,MIN(Inputs!$B$7,J3+K3)) | M3: =L3-K3 | N3: =IF(J3<=0.005,0,MIN(H3,J3-M3)) | O3: =ROUND(J3-M3-N3,2)
A4: 2 | B4: =EDATE(Inputs!$B$6,A4-1) | C4: =G3 | D4: =IF(C4<=0.005,0,ROUND(C4*Inputs!$B$8,2)) | E4: =IF(C4<=0.005,0,MIN(Inputs!$B$7,C4+D4)) | F4: =E4-D4 | G4: =ROUND(C4-F4,2) | H4: 0 | I4: =IF(H4=0,"",IF(A4<2,"X not before month 2",IF(H4<MAX(5000,Inputs!$B$7),"X below min",IF(H4>MIN(5000000,0.75*J4),"X above max","OK")))) | J4: =O3 | K4: =IF(J4<=0.005,0,ROUND(J4*Inputs!$B$8,2)) | L4: =IF(J4<=0.005,0,MIN(Inputs!$B$7,J4+K4)) | M4: =L4-K4 | N4: =IF(J4<=0.005,0,MIN(H4,J4-M4)) | O4: =ROUND(J4-M4-N4,2)
A5: 3 | B5: =EDATE(Inputs!$B$6,A5-1) | C5: =G4 | D5: =IF(C5<=0.005,0,ROUND(C5*Inputs!$B$8,2)) | E5: =IF(C5<=0.005,0,MIN(Inputs!$B$7,C5+D5)) | F5: =E5-D5 | G5: =ROUND(C5-F5,2) | H5: 0 | I5: =IF(H5=0,"",IF(A5<2,"X not before month 2",IF(H5<MAX(5000,Inputs!$B$7),"X below min",IF(H5>MIN(5000000,0.75*J5),"X above max","OK")))) | J5: =O4 | K5: =IF(J5<=0.005,0,ROUND(J5*Inputs!$B$8,2)) | L5: =IF(J5<=0.005,0,MIN(Inputs!$B$7,J5+K5)) | M5: =L5-K5 | N5: =IF(J5<=0.005,0,MIN(H5,J5-M5)) | O5: =ROUND(J5-M5-N5,2)
A6: 4 | B6: =EDATE(Inputs!$B$6,A6-1) | C6: =G5 | D6: =IF(C6<=0.005,0,ROUND(C6*Inputs!$B$8,2)) | E6: =IF(C6<=0.005,0,MIN(Inputs!$B$7,C6+D6)) | F6: =E6-D6 | G6: =ROUND(C6-F6,2) | H6: 0 | I6: =IF(H6=0,"",IF(A6<2,"X not before month 2",IF(H6<MAX(5000,Inputs!$B$7),"X below min",IF(H6>MIN(5000000,0.75*J6),"X above max","OK")))) | J6: =O5 | K6: =IF(J6<=0.005,0,ROUND(J6*Inputs!$B$8,2)) | L6: =IF(J6<=0.005,0,MIN(Inputs!$B$7,J6+K6)) | M6: =L6-K6 | N6: =IF(J6<=0.005,0,MIN(H6,J6-M6)) | O6: =ROUND(J6-M6-N6,2)
A7: 5 | B7: =EDATE(Inputs!$B$6,A7-1) | C7: =G6 | D7: =IF(C7<=0.005,0,ROUND(C7*Inputs!$B$8,2)) | E7: =IF(C7<=0.005,0,MIN(Inputs!$B$7,C7+D7)) | F7: =E7-D7 | G7: =ROUND(C7-F7,2) | H7: 0 | I7: =IF(H7=0,"",IF(A7<2,"X not before month 2",IF(H7<MAX(5000,Inputs!$B$7),"X below min",IF(H7>MIN(5000000,0.75*J7),"X above max","OK")))) | J7: =O6 | K7: =IF(J7<=0.005,0,ROUND(J7*Inputs!$B$8,2)) | L7: =IF(J7<=0.005,0,MIN(Inputs!$B$7,J7+K7)) | M7: =L7-K7 | N7: =IF(J7<=0.005,0,MIN(H7,J7-M7)) | O7: =ROUND(J7-M7-N7,2)
A8: 6 | B8: =EDATE(Inputs!$B$6,A8-1) | C8: =G7 | D8: =IF(C8<=0.005,0,ROUND(C8*Inputs!$B$8,2)) | E8: =IF(C8<=0.005,0,MIN(Inputs!$B$7,C8+D8)) | F8: =E8-D8 | G8: =ROUND(C8-F8,2) | H8: 0 | I8: =IF(H8=0,"",IF(A8<2,"X not before month 2",IF(H8<MAX(5000,Inputs!$B$7),"X below min",IF(H8>MIN(5000000,0.75*J8),"X above max","OK")))) | J8: =O7 | K8: =IF(J8<=0.005,0,ROUND(J8*Inputs!$B$8,2)) | L8: =IF(J8<=0.005,0,MIN(Inputs!$B$7,J8+K8)) | M8: =L8-K8 | N8: =IF(J8<=0.005,0,MIN(H8,J8-M8)) | O8: =ROUND(J8-M8-N8,2)
A9: 7 | B9: =EDATE(Inputs!$B$6,A9-1) | C9: =G8 | D9: =IF(C9<=0.005,0,ROUND(C9*Inputs!$B$8,2)) | E9: =IF(C9<=0.005,0,MIN(Inputs!$B$7,C9+D9)) | F9: =E9-D9 | G9: =ROUND(C9-F9,2) | H9: 0 | I9: =IF(H9=0,"",IF(A9<2,"X not before month 2",IF(H9<MAX(5000,Inputs!$B$7),"X below min",IF(H9>MIN(5000000,0.75*J9),"X above max","OK")))) | J9: =O8 | K9: =IF(J9<=0.005,0,ROUND(J9*Inputs!$B$8,2)) | L9: =IF(J9<=0.005,0,MIN(Inputs!$B$7,J9+K9)) | M9: =L9-K9 | N9: =IF(J9<=0.005,0,MIN(H9,J9-M9)) | O9: =ROUND(J9-M9-N9,2)
A10: 8 | B10: =EDATE(Inputs!$B$6,A10-1) | C10: =G9 | D10: =IF(C10<=0.005,0,ROUND(C10*Inputs!$B$8,2)) | E10: =IF(C10<=0.005,0,MIN(Inputs!$B$7,C10+D10)) | F10: =E10-D10 | G10: =ROUND(C10-F10,2) | H10: 0 | I10: =IF(H10=0,"",IF(A10<2,"X not before month 2",IF(H10<MAX(5000,Inputs!$B$7),"X below min",IF(H10>MIN(5000000,0.75*J10),"X above max","OK")))) | J10: =O9 | K10: =IF(J10<=0.005,0,ROUND(J10*Inputs!$B$8,2)) | L10: =IF(J10<=0.005,0,MIN(Inputs!$B$7,J10+K10)) | M10: =L10-K10 | N10: =IF(J10<=0.005,0,MIN(H10,J10-M10)) | O10: =ROUND(J10-M10-N10,2)
A11: 9 | B11: =EDATE(Inputs!$B$6,A11-1) | C11: =G10 | D11: =IF(C11<=0.005,0,ROUND(C11*Inputs!$B$8,2)) | E11: =IF(C11<=0.005,0,MIN(Inputs!$B$7,C11+D11)) | F11: =E11-D11 | G11: =ROUND(C11-F11,2) | H11: 0 | I11: =IF(H11=0,"",IF(A11<2,"X not before month 2",IF(H11<MAX(5000,Inputs!$B$7),"X below min",IF(H11>MIN(5000000,0.75*J11),"X above max","OK")))) | J11: =O10 | K11: =IF(J11<=0.005,0,ROUND(J11*Inputs!$B$8,2)) | L11: =IF(J11<=0.005,0,MIN(Inputs!$B$7,J11+K11)) | M11: =L11-K11 | N11: =IF(J11<=0.005,0,MIN(H11,J11-M11)) | O11: =ROUND(J11-M11-N11,2)
A12: 10 | B12: =EDATE(Inputs!$B$6,A12-1) | C12: =G11 | D12: =IF(C12<=0.005,0,ROUND(C12*Inputs!$B$8,2)) | E12: =IF(C12<=0.005,0,MIN(Inputs!$B$7,C12+D12)) | F12: =E12-D12 | G12: =ROUND(C12-F12,2) | H12: 0 | I12: =IF(H12=0,"",IF(A12<2,"X not before month 2",IF(H12<MAX(5000,Inputs!$B$7),"X below min",IF(H12>MIN(5000000,0.75*J12),"X above max","OK")))) | J12: =O11 | K12: =IF(J12<=0.005,0,ROUND(J12*Inputs!$B$8,2)) | L12: =IF(J12<=0.005,0,MIN(Inputs!$B$7,J12+K12)) | M12: =L12-K12 | N12: =IF(J12<=0.005,0,MIN(H12,J12-M12)) | O12: =ROUND(J12-M12-N12,2)
A13: 11 | B13: =EDATE(Inputs!$B$6,A13-1) | C13: =G12 | D13: =IF(C13<=0.005,0,ROUND(C13*Inputs!$B$8,2)) | E13: =IF(C13<=0.005,0,MIN(Inputs!$B$7,C13+D13)) | F13: =E13-D13 | G13: =ROUND(C13-F13,2) | H13: 0 | I13: =IF(H13=0,"",IF(A13<2,"X not before month 2",IF(H13<MAX(5000,Inputs!$B$7),"X below min",IF(H13>MIN(5000000,0.75*J13),"X above max","OK")))) | J13: =O12 | K13: =IF(J13<=0.005,0,ROUND(J13*Inputs!$B$8,2)) | L13: =IF(J13<=0.005,0,MIN(Inputs!$B$7,J13+K13)) | M13: =L13-K13 | N13: =IF(J13<=0.005,0,MIN(H13,J13-M13)) | O13: =ROUND(J13-M13-N13,2)
A14: 12 | B14: =EDATE(Inputs!$B$6,A14-1) | C14: =G13 | D14: =IF(C14<=0.005,0,ROUND(C14*Inputs!$B$8,2)) | E14: =IF(C14<=0.005,0,MIN(Inputs!$B$7,C14+D14)) | F14: =E14-D14 | G14: =ROUND(C14-F14,2) | H14: 0 | I14: =IF(H14=0,"",IF(A14<2,"X not before month 2",IF(H14<MAX(5000,Inputs!$B$7),"X below min",IF(H14>MIN(5000000,0.75*J14),"X above max","OK")))) | J14: =O13 | K14: =IF(J14<=0.005,0,ROUND(J14*Inputs!$B$8,2)) | L14: =IF(J14<=0.005,0,MIN(Inputs!$B$7,J14+K14)) | M14: =L14-K14 | N14: =IF(J14<=0.005,0,MIN(H14,J14-M14)) | O14: =ROUND(J14-M14-N14,2)
A15: 13 | B15: =EDATE(Inputs!$B$6,A15-1) | C15: =G14 | D15: =IF(C15<=0.005,0,ROUND(C15*Inputs!$B$8,2)) | E15: =IF(C15<=0.005,0,MIN(Inputs!$B$7,C15+D15)) | F15: =E15-D15 | G15: =ROUND(C15-F15,2) | H15: 0 | I15: =IF(H15=0,"",IF(A15<2,"X not before month 2",IF(H15<MAX(5000,Inputs!$B$7),"X below min",IF(H15>MIN(5000000,0.75*J15),"X above max","OK")))) | J15: =O14 | K15: =IF(J15<=0.005,0,ROUND(J15*Inputs!$B$8,2)) | L15: =IF(J15<=0.005,0,MIN(Inputs!$B$7,J15+K15)) | M15: =L15-K15 | N15: =IF(J15<=0.005,0,MIN(H15,J15-M15)) | O15: =ROUND(J15-M15-N15,2)
... A182: 180 | B182: =EDATE(Inputs!$B$6,A182-1) | C182: =G181 | D182: =IF(C182<=0.005,0,ROUND(C182*Inputs!$B$8,2)) | E182: =IF(C182<=0.005,0,MIN(Inputs!$B$7,C182+D182)) | F182: =E182-D182 | G182: =ROUND(C182-F182,2) | H182: 0 | I182: =IF(H182=0,"",IF(A182<2,"X not before month 2",IF(H182<MAX(5000,Inputs!$B$7),"X below min",IF(H182>MIN(5000000,0.75*J182),"X above max","OK")))) | J182: =O181 | K182: =IF(J182<=0.005,0,ROUND(J182*Inputs!$B$8,2)) | L182: =IF(J182<=0.005,0,MIN(Inputs!$B$7,J182+K182)) | M182: =L182-K182 | N182: =IF(J182<=0.005,0,MIN(H182,J182-M182)) | O182: =ROUND(J182-M182-N182,2)

Sheet Schedule_B
A1: AMORTIZATION SCHEDULE — Loan B | D1: (C-G: baseline, no prepayment | H: type any extra payment | J-P: your plan)
A2: Month | B2: Date | C2: Opening | D2: Interest | E2: EMI | F2: Principal | G2: Closing | H2: PREPAY (edit) | I2: Rule check | J2: Opening | K2: Interest | L2: EMI | M2: Principal | N2: Prepay | O2: Closing
A3: 1 | B3: =EDATE(Inputs!$C$6,A3-1) | C3: =Inputs!$C$3 | D3: =IF(C3<=0.005,0,ROUND(C3*Inputs!$C$8,2)) | E3: =IF(C3<=0.005,0,MIN(Inputs!$C$7,C3+D3)) | F3: =E3-D3 | G3: =ROUND(C3-F3,2) | H3: 0 | I3: =IF(H3=0,"",IF(A3<2,"X not before month 2",IF(H3<MAX(5000,Inputs!$C$7),"X below min",IF(H3>MIN(5000000,0.75*J3),"X above max","OK")))) | J3: =Inputs!$C$3 | K3: =IF(J3<=0.005,0,ROUND(J3*Inputs!$C$8,2)) | L3: =IF(J3<=0.005,0,MIN(Inputs!$C$7,J3+K3)) | M3: =L3-K3 | N3: =IF(J3<=0.005,0,MIN(H3,J3-M3)) | O3: =ROUND(J3-M3-N3,2)
A4: 2 | B4: =EDATE(Inputs!$C$6,A4-1) | C4: =G3 | D4: =IF(C4<=0.005,0,ROUND(C4*Inputs!$C$8,2)) | E4: =IF(C4<=0.005,0,MIN(Inputs!$C$7,C4+D4)) | F4: =E4-D4 | G4: =ROUND(C4-F4,2) | H4: 0 | I4: =IF(H4=0,"",IF(A4<2,"X not before month 2",IF(H4<MAX(5000,Inputs!$C$7),"X below min",IF(H4>MIN(5000000,0.75*J4),"X above max","OK")))) | J4: =O3 | K4: =IF(J4<=0.005,0,ROUND(J4*Inputs!$C$8,2)) | L4: =IF(J4<=0.005,0,MIN(Inputs!$C$7,J4+K4)) | M4: =L4-K4 | N4: =IF(J4<=0.005,0,MIN(H4,J4-M4)) | O4: =ROUND(J4-M4-N4,2)
A5: 3 | B5: =EDATE(Inputs!$C$6,A5-1) | C5: =G4 | D5: =IF(C5<=0.005,0,ROUND(C5*Inputs!$C$8,2)) | E5: =IF(C5<=0.005,0,MIN(Inputs!$C$7,C5+D5)) | F5: =E5-D5 | G5: =ROUND(C5-F5,2) | H5: 0 | I5: =IF(H5=0,"",IF(A5<2,"X not before month 2",IF(H5<MAX(5000,Inputs!$C$7),"X below min",IF(H5>MIN(5000000,0.75*J5),"X above max","OK")))) | J5: =O4 | K5: =IF(J5<=0.005,0,ROUND(J5*Inputs!$C$8,2)) | L5: =IF(J5<=0.005,0,MIN(Inputs!$C$7,J5+K5)) | M5: =L5-K5 | N5: =IF(J5<=0.005,0,MIN(H5,J5-M5)) | O5: =ROUND(J5-M5-N5,2)
A6: 4 | B6: =EDATE(Inputs!$C$6,A6-1) | C6: =G5 | D6: =IF(C6<=0.005,0,ROUND(C6*Inputs!$C$8,2)) | E6: =IF(C6<=0.005,0,MIN(Inputs!$C$7,C6+D6)) | F6: =E6-D6 | G6: =ROUND(C6-F6,2) | H6: 0 | I6: =IF(H6=0,"",IF(A6<2,"X not before month 2",IF(H6<MAX(5000,Inputs!$C$7),"X below min",IF(H6>MIN(5000000,0.75*J6),"X above max","OK")))) | J6: =O5 | K6: =IF(J6<=0.005,0,ROUND(J6*Inputs!$C$8,2)) | L6: =IF(J6<=0.005,0,MIN(Inputs!$C$7,J6+K6)) | M6: =L6-K6 | N6: =IF(J6<=0.005,0,MIN(H6,J6-M6)) | O6: =ROUND(J6-M6-N6,2)
A7: 5 | B7: =EDATE(Inputs!$C$6,A7-1) | C7: =G6 | D7: =IF(C7<=0.005,0,ROUND(C7*Inputs!$C$8,2)) | E7: =IF(C7<=0.005,0,MIN(Inputs!$C$7,C7+D7)) | F7: =E7-D7 | G7: =ROUND(C7-F7,2) | H7: 0 | I7: =IF(H7=0,"",IF(A7<2,"X not before month 2",IF(H7<MAX(5000,Inputs!$C$7),"X below min",IF(H7>MIN(5000000,0.75*J7),"X above max","OK")))) | J7: =O6 | K7: =IF(J7<=0.005,0,ROUND(J7*Inputs!$C$8,2)) | L7: =IF(J7<=0.005,0,MIN(Inputs!$C$7,J7+K7)) | M7: =L7-K7 | N7: =IF(J7<=0.005,0,MIN(H7,J7-M7)) | O7: =ROUND(J7-M7-N7,2)
A8: 6 | B8: =EDATE(Inputs!$C$6,A8-1) | C8: =G7 | D8: =IF(C8<=0.005,0,ROUND(C8*Inputs!$C$8,2)) | E8: =IF(C8<=0.005,0,MIN(Inputs!$C$7,C8+D8)) | F8: =E8-D8 | G8: =ROUND(C8-F8,2) | H8: 0 | I8: =IF(H8=0,"",IF(A8<2,"X not before month 2",IF(H8<MAX(5000,Inputs!$C$7),"X below min",IF(H8>MIN(5000000,0.75*J8),"X above max","OK")))) | J8: =O7 | K8: =IF(J8<=0.005,0,ROUND(J8*Inputs!$C$8,2)) | L8: =IF(J8<=0.005,0,MIN(Inputs!$C$7,J8+K8)) | M8: =L8-K8 | N8: =IF(J8<=0.005,0,MIN(H8,J8-M8)) | O8: =ROUND(J8-M8-N8,2)
A9: 7 | B9: =EDATE(Inputs!$C$6,A9-1) | C9: =G8 | D9: =IF(C9<=0.005,0,ROUND(C9*Inputs!$C$8,2)) | E9: =IF(C9<=0.005,0,MIN(Inputs!$C$7,C9+D9)) | F9: =E9-D9 | G9: =ROUND(C9-F9,2) | H9: 0 | I9: =IF(H9=0,"",IF(A9<2,"X not before month 2",IF(H9<MAX(5000,Inputs!$C$7),"X below min",IF(H9>MIN(5000000,0.75*J9),"X above max","OK")))) | J9: =O8 | K9: =IF(J9<=0.005,0,ROUND(J9*Inputs!$C$8,2)) | L9: =IF(J9<=0.005,0,MIN(Inputs!$C$7,J9+K9)) | M9: =L9-K9 | N9: =IF(J9<=0.005,0,MIN(H9,J9-M9)) | O9: =ROUND(J9-M9-N9,2)
A10: 8 | B10: =EDATE(Inputs!$C$6,A10-1) | C10: =G9 | D10: =IF(C10<=0.005,0,ROUND(C10*Inputs!$C$8,2)) | E10: =IF(C10<=0.005,0,MIN(Inputs!$C$7,C10+D10)) | F10: =E10-D10 | G10: =ROUND(C10-F10,2) | H10: 0 | I10: =IF(H10=0,"",IF(A10<2,"X not before month 2",IF(H10<MAX(5000,Inputs!$C$7),"X below min",IF(H10>MIN(5000000,0.75*J10),"X above max","OK")))) | J10: =O9 | K10: =IF(J10<=0.005,0,ROUND(J10*Inputs!$C$8,2)) | L10: =IF(J10<=0.005,0,MIN(Inputs!$C$7,J10+K10)) | M10: =L10-K10 | N10: =IF(J10<=0.005,0,MIN(H10,J10-M10)) | O10: =ROUND(J10-M10-N10,2)
A11: 9 | B11: =EDATE(Inputs!$C$6,A11-1) | C11: =G10 | D11: =IF(C11<=0.005,0,ROUND(C11*Inputs!$C$8,2)) | E11: =IF(C11<=0.005,0,MIN(Inputs!$C$7,C11+D11)) | F11: =E11-D11 | G11: =ROUND(C11-F11,2) | H11: 0 | I11: =IF(H11=0,"",IF(A11<2,"X not before month 2",IF(H11<MAX(5000,Inputs!$C$7),"X below min",IF(H11>MIN(5000000,0.75*J11),"X above max","OK")))) | J11: =O10 | K11: =IF(J11<=0.005,0,ROUND(J11*Inputs!$C$8,2)) | L11: =IF(J11<=0.005,0,MIN(Inputs!$C$7,J11+K11)) | M11: =L11-K11 | N11: =IF(J11<=0.005,0,MIN(H11,J11-M11)) | O11: =ROUND(J11-M11-N11,2)
A12: 10 | B12: =EDATE(Inputs!$C$6,A12-1) | C12: =G11 | D12: =IF(C12<=0.005,0,ROUND(C12*Inputs!$C$8,2)) | E12: =IF(C12<=0.005,0,MIN(Inputs!$C$7,C12+D12)) | F12: =E12-D12 | G12: =ROUND(C12-F12,2) | H12: 0 | I12: =IF(H12=0,"",IF(A12<2,"X not before month 2",IF(H12<MAX(5000,Inputs!$C$7),"X below min",IF(H12>MIN(5000000,0.75*J12),"X above max","OK")))) | J12: =O11 | K12: =IF(J12<=0.005,0,ROUND(J12*Inputs!$C$8,2)) | L12: =IF(J12<=0.005,0,MIN(Inputs!$C$7,J12+K12)) | M12: =L12-K12 | N12: =IF(J12<=0.005,0,MIN(H12,J12-M12)) | O12: =ROUND(J12-M12-N12,2)
A13: 11 | B13: =EDATE(Inputs!$C$6,A13-1) | C13: =G12 | D13: =IF(C13<=0.005,0,ROUND(C13*Inputs!$C$8,2)) | E13: =IF(C13<=0.005,0,MIN(Inputs!$C$7,C13+D13)) | F13: =E13-D13 | G13: =ROUND(C13-F13,2) | H13: 0 | I13: =IF(H13=0,"",IF(A13<2,"X not before month 2",IF(H13<MAX(5000,Inputs!$C$7),"X below min",IF(H13>MIN(5000000,0.75*J13),"X above max","OK")))) | J13: =O12 | K13: =IF(J13<=0.005,0,ROUND(J13*Inputs!$C$8,2)) | L13: =IF(J13<=0.005,0,MIN(Inputs!$C$7,J13+K13)) | M13: =L13-K13 | N13: =IF(J13<=0.005,0,MIN(H13,J13-M13)) | O13: =ROUND(J13-M13-N13,2)
A14: 12 | B14: =EDATE(Inputs!$C$6,A14-1) | C14: =G13 | D14: =IF(C14<=0.005,0,ROUND(C14*Inputs!$C$8,2)) | E14: =IF(C14<=0.005,0,MIN(Inputs!$C$7,C14+D14)) | F14: =E14-D14 | G14: =ROUND(C14-F14,2) | H14: 0 | I14: =IF(H14=0,"",IF(A14<2,"X not before month 2",IF(H14<MAX(5000,Inputs!$C$7),"X below min",IF(H14>MIN(5000000,0.75*J14),"X above max","OK")))) | J14: =O13 | K14: =IF(J14<=0.005,0,ROUND(J14*Inputs!$C$8,2)) | L14: =IF(J14<=0.005,0,MIN(Inputs!$C$7,J14+K14)) | M14: =L14-K14 | N14: =IF(J14<=0.005,0,MIN(H14,J14-M14)) | O14: =ROUND(J14-M14-N14,2)
A15: 13 | B15: =EDATE(Inputs!$C$6,A15-1) | C15: =G14 | D15: =IF(C15<=0.005,0,ROUND(C15*Inputs!$C$8,2)) | E15: =IF(C15<=0.005,0,MIN(Inputs!$C$7,C15+D15)) | F15: =E15-D15 | G15: =ROUND(C15-F15,2) | H15: 0 | I15: =IF(H15=0,"",IF(A15<2,"X not before month 2",IF(H15<MAX(5000,Inputs!$C$7),"X below min",IF(H15>MIN(5000000,0.75*J15),"X above max","OK")))) | J15: =O14 | K15: =IF(J15<=0.005,0,ROUND(J15*Inputs!$C$8,2)) | L15: =IF(J15<=0.005,0,MIN(Inputs!$C$7,J15+K15)) | M15: =L15-K15 | N15: =IF(J15<=0.005,0,MIN(H15,J15-M15)) | O15: =ROUND(J15-M15-N15,2)
... A182: 180 | B182: =EDATE(Inputs!$C$6,A182-1) | C182: =G181 | D182: =IF(C182<=0.005,0,ROUND(C182*Inputs!$C$8,2)) | E182: =IF(C182<=0.005,0,MIN(Inputs!$C$7,C182+D182)) | F182: =E182-D182 | G182: =ROUND(C182-F182,2) | H182: 0 | I182: =IF(H182=0,"",IF(A182<2,"X not before month 2",IF(H182<MAX(5000,Inputs!$C$7),"X below min",IF(H182>MIN(5000000,0.75*J182),"X above max","OK")))) | J182: =O181 | K182: =IF(J182<=0.005,0,ROUND(J182*Inputs!$C$8,2)) | L182: =IF(J182<=0.005,0,MIN(Inputs!$C$7,J182+K182)) | M182: =L182-K182 | N182: =IF(J182<=0.005,0,MIN(H182,J182-M182)) | O182: =ROUND(J182-M182-N182,2)

Sheet Summary
A1: SUMMARY — baseline vs your prepayment plan
B3: Loan A | C3: Loan B | D3: Combined
A4: Outstanding (Rs) | B4: =Inputs!B3 | C4: =Inputs!C3 | D4: =B4+C4
A5: Monthly EMI (Rs) | B5: =Inputs!B7 | C5: =Inputs!C7 | D5: =B5+C5
A6: Baseline total interest (Rs) | B6: =SUM(Schedule_A!D3:D182) | C6: =SUM(Schedule_B!D3:D182) | D6: =B6+C6
A7: Plan total interest (Rs) | B7: =SUM(Schedule_A!K3:K182) | C7: =SUM(Schedule_B!K3:K182) | D7: =B7+C7
A8: INTEREST SAVED (Rs) | B8: =B6-B7 | C8: =C6-C7 | D8: =B8+C8
A9: Baseline payoff (months) | B9: =COUNTIF(Schedule_A!E3:E182,">0.005") | C9: =COUNTIF(Schedule_B!E3:E182,">0.005")
A10: Plan payoff (months) | B10: =COUNTIF(Schedule_A!L3:L182,">0.005") | C10: =COUNTIF(Schedule_B!L3:L182,">0.005")
A11: MONTHS SAVED | B11: =B9-B10 | C11: =C9-C10
A12: Years saved | B12: =B11/12 | C12: =C11/12
A13: Baseline payoff date | B13: =EDATE(Inputs!B6,B9-1) | C13: =EDATE(Inputs!C6,C9-1)
A14: Plan payoff date | B14: =EDATE(Inputs!B6,B10-1) | C14: =EDATE(Inputs!C6,C10-1)
A16: Prepay FIRST: | B16: =IF(Inputs!B4>Inputs!C4,"Loan A (higher rate)",IF(Inputs!C4>Inputs!B4,"Loan B (higher rate)",IF(Inputs!B3>=Inputs!C3,"Loan B (larger balance saves more)","Loan A (larger balance saves more)")))
A17: Note: pre-EMI is interest-only and does not change months/interest saved above.
A18: Pre-EMI interest (one-time) | B18: =Inputs!B9 | C18: =Inputs!C9 | D18: =B18+C18
A19: Total interest incl. pre-EMI (plan) | B19: =B7+B18 | C19: =C7+C18 | D19: =B19+C19

Sheet Windfall What-If
A1: WINDFALL WHAT-IF — one lump sum, which loan saves more?
A3: Lump sum (Rs): | B3: 500000
A4: Apply in month #: | B4: 12
A6: Loan A — interest saved (Rs): | B6: =SUM(Schedule_A!D3:D182)-SUM(C186:C365)
A7: Loan A — months saved: | B7: =COUNTIF(Schedule_A!E3:E182,">0.005")-COUNTIF(D186:D365,">0.005")
A8: Loan B — interest saved (Rs): | B8: =SUM(Schedule_B!D3:D182)-SUM(J186:J365)
A9: Loan B — months saved: | B9: =COUNTIF(Schedule_B!E3:E182,">0.005")-COUNTIF(K186:K365,">0.005")
A10: RECOMMENDATION: | B10: =IF(B6>B8,"Put it on Loan A (saves more interest)",IF(B8>B6,"Put it on Loan B (saves more interest)","Either — equal saving"))
A185: Month | B185: Opening | C185: Interest | D185: EMI | E185: Prepay | F185: Closing | H185: Month | I185: Opening | J185: Interest | K185: EMI | L185: Prepay | M185: Closing
A186: 1 | B186: =Inputs!$B$3 | C186: =IF(B186<=0.005,0,ROUND(B186*Inputs!$B$8,2)) | D186: =IF(B186<=0.005,0,MIN(Inputs!$B$7,B186+C186)) | E186: =IF(B186<=0.005,0,IF(A186=$B$4,MIN($B$3,B186-(D186-C186)),0)) | F186: =ROUND(B186-(D186-C186)-E186,2) | H186: 1 | I186: =Inputs!$C$3 | J186: =IF(I186<=0.005,0,ROUND(I186*Inputs!$C$8,2)) | K186: =IF(I186<=0.005,0,MIN(Inputs!$C$7,I186+J186)) | L186: =IF(I186<=0.005,0,IF(H186=$B$4,MIN($B$3,I186-(K186-J186)),0)) | M186: =ROUND(I186-(K186-J186)-L186,2)
A187: 2 | B187: =F186 | C187: =IF(B187<=0.005,0,ROUND(B187*Inputs!$B$8,2)) | D187: =IF(B187<=0.005,0,MIN(Inputs!$B$7,B187+C187)) | E187: =IF(B187<=0.005,0,IF(A187=$B$4,MIN($B$3,B187-(D187-C187)),0)) | F187: =ROUND(B187-(D187-C187)-E187,2) | H187: 2 | I187: =M186 | J187: =IF(I187<=0.005,0,ROUND(I187*Inputs!$C$8,2)) | K187: =IF(I187<=0.005,0,MIN(Inputs!$C$7,I187+J187)) | L187: =IF(I187<=0.005,0,IF(H187=$B$4,MIN($B$3,I187-(K187-J187)),0)) | M187: =ROUND(I187-(K187-J187)-L187,2)
A188: 3 | B188: =F187 | C188: =IF(B188<=0.005,0,ROUND(B188*Inputs!$B$8,2)) | D188: =IF(B188<=0.005,0,MIN(Inputs!$B$7,B188+C188)) | E188: =IF(B188<=0.005,0,IF(A188=$B$4,MIN($B$3,B188-(D188-C188)),0)) | F188: =ROUND(B188-(D188-C188)-E188,2) | H188: 3 | I188: =M187 | J188: =IF(I188<=0.005,0,ROUND(I188*Inputs!$C$8,2)) | K188: =IF(I188<=0.005,0,MIN(Inputs!$C$7,I188+J188)) | L188: =IF(I188<=0.005,0,IF(H188=$B$4,MIN($B$3,I188-(K188-J188)),0)) | M188: =ROUND(I188-(K188-J188)-L188,2)
A189: 4 | B189: =F188 | C189: =IF(B189<=0.005,0,ROUND(B189*Inputs!$B$8,2)) | D189: =IF(B189<=0.005,0,MIN(Inputs!$B$7,B189+C189)) | E189: =IF(B189<=0.005,0,IF(A189=$B$4,MIN($B$3,B189-(D189-C189)),0)) | F189: =ROUND(B189-(D189-C189)-E189,2) | H189: 4 | I189: =M188 | J189: =IF(I189<=0.005,0,ROUND(I189*Inputs!$C$8,2)) | K189: =IF(I189<=0.005,0,MIN(Inputs!$C$7,I189+J189)) | L189: =IF(I189<=0.005,0,IF(H189=$B$4,MIN($B$3,I189-(K189-J189)),0)) | M189: =ROUND(I189-(K189-J189)-L189,2)
A190: 5 | B190: =F189 | C190: =IF(B190<=0.005,0,ROUND(B190*Inputs!$B$8,2)) | D190: =IF(B190<=0.005,0,MIN(Inputs!$B$7,B190+C190)) | E190: =IF(B190<=0.005,0,IF(A190=$B$4,MIN($B$3,B190-(D190-C190)),0)) | F190: =ROUND(B190-(D190-C190)-E190,2) | H190: 5 | I190: =M189 | J190: =IF(I190<=0.005,0,ROUND(I190*Inputs!$C$8,2)) | K190: =IF(I190<=0.005,0,MIN(Inputs!$C$7,I190+J190)) | L190: =IF(I190<=0.005,0,IF(H190=$B$4,MIN($B$3,I190-(K190-J190)),0)) | M190: =ROUND(I190-(K190-J190)-L190,2)
A191: 6 | B191: =F190 | C191: =IF(B191<=0.005,0,ROUND(B191*Inputs!$B$8,2)) | D191: =IF(B191<=0.005,0,MIN(Inputs!$B$7,B191+C191)) | E191: =IF(B191<=0.005,0,IF(A191=$B$4,MIN($B$3,B191-(D191-C191)),0)) | F191: =ROUND(B191-(D191-C191)-E191,2) | H191: 6 | I191: =M190 | J191: =IF(I191<=0.005,0,ROUND(I191*Inputs!$C$8,2)) | K191: =IF(I191<=0.005,0,MIN(Inputs!$C$7,I191+J191)) | L191: =IF(I191<=0.005,0,IF(H191=$B$4,MIN($B$3,I191-(K191-J191)),0)) | M191: =ROUND(I191-(K191-J191)-L191,2)
A192: 7 | B192: =F191 | C192: =IF(B192<=0.005,0,ROUND(B192*Inputs!$B$8,2)) | D192: =IF(B192<=0.005,0,MIN(Inputs!$B$7,B192+C192)) | E192: =IF(B192<=0.005,0,IF(A192=$B$4,MIN($B$3,B192-(D192-C192)),0)) | F192: =ROUND(B192-(D192-C192)-E192,2) | H192: 7 | I192: =M191 | J192: =IF(I192<=0.005,0,ROUND(I192*Inputs!$C$8,2)) | K192: =IF(I192<=0.005,0,MIN(Inputs!$C$7,I192+J192)) | L192: =IF(I192<=0.005,0,IF(H192=$B$4,MIN($B$3,I192-(K192-J192)),0)) | M192: =ROUND(I192-(K192-J192)-L192,2)
A193: 8 | B193: =F192 | C193: =IF(B193<=0.005,0,ROUND(B193*Inputs!$B$8,2)) | D193: =IF(B193<=0.005,0,MIN(Inputs!$B$7,B193+C193)) | E193: =IF(B193<=0.005,0,IF(A193=$B$4,MIN($B$3,B193-(D193-C193)),0)) | F193: =ROUND(B193-(D193-C193)-E193,2) | H193: 8 | I193: =M192 | J193: =IF(I193<=0.005,0,ROUND(I193*Inputs!$C$8,2)) | K193: =IF(I193<=0.005,0,MIN(Inputs!$C$7,I193+J193)) | L193: =IF(I193<=0.005,0,IF(H193=$B$4,MIN($B$3,I193-(K193-J193)),0)) | M193: =ROUND(I193-(K193-J193)-L193,2)
A194: 9 | B194: =F193 | C194: =IF(B194<=0.005,0,ROUND(B194*Inputs!$B$8,2)) | D194: =IF(B194<=0.005,0,MIN(Inputs!$B$7,B194+C194)) | E194: =IF(B194<=0.005,0,IF(A194=$B$4,MIN($B$3,B194-(D194-C194)),0)) | F194: =ROUND(B194-(D194-C194)-E194,2) | H194: 9 | I194: =M193 | J194: =IF(I194<=0.005,0,ROUND(I194*Inputs!$C$8,2)) | K194: =IF(I194<=0.005,0,MIN(Inputs!$C$7,I194+J194)) | L194: =IF(I194<=0.005,0,IF(H194=$B$4,MIN($B$3,I194-(K194-J194)),0)) | M194: =ROUND(I194-(K194-J194)-L194,2)
A195: 10 | B195: =F194 | C195: =IF(B195<=0.005,0,ROUND(B195*Inputs!$B$8,2)) | D195: =IF(B195<=0.005,0,MIN(Inputs!$B$7,B195+C195)) | E195: =IF(B195<=0.005,0,IF(A195=$B$4,MIN($B$3,B195-(D195-C195)),0)) | F195: =ROUND(B195-(D195-C195)-E195,2) | H195: 10 | I195: =M194 | J195: =IF(I195<=0.005,0,ROUND(I195*Inputs!$C$8,2)) | K195: =IF(I195<=0.005,0,MIN(Inputs!$C$7,I195+J195)) | L195: =IF(I195<=0.005,0,IF(H195=$B$4,MIN($B$3,I195-(K195-J195)),0)) | M195: =ROUND(I195-(K195-J195)-L195,2)
A196: 11 | B196: =F195 | C196: =IF(B196<=0.005,0,ROUND(B196*Inputs!$B$8,2)) | D196: =IF(B196<=0.005,0,MIN(Inputs!$B$7,B196+C196)) | E196: =IF(B196<=0.005,0,IF(A196=$B$4,MIN($B$3,B196-(D196-C196)),0)) | F196: =ROUND(B196-(D196-C196)-E196,2) | H196: 11 | I196: =M195 | J196: =IF(I196<=0.005,0,ROUND(I196*Inputs!$C$8,2)) | K196: =IF(I196<=0.005,0,MIN(Inputs!$C$7,I196+J196)) | L196: =IF(I196<=0.005,0,IF(H196=$B$4,MIN($B$3,I196-(K196-J196)),0)) | M196: =ROUND(I196-(K196-J196)-L196,2)
A197: 12 | B197: =F196 | C197: =IF(B197<=0.005,0,ROUND(B197*Inputs!$B$8,2)) | D197: =IF(B197<=0.005,0,MIN(Inputs!$B$7,B197+C197)) | E197: =IF(B197<=0.005,0,IF(A197=$B$4,MIN($B$3,B197-(D197-C197)),0)) | F197: =ROUND(B197-(D197-C197)-E197,2) | H197: 12 | I197: =M196 | J197: =IF(I197<=0.005,0,ROUND(I197*Inputs!$C$8,2)) | K197: =IF(I197<=0.005,0,MIN(Inputs!$C$7,I197+J197)) | L197: =IF(I197<=0.005,0,IF(H197=$B$4,MIN($B$3,I197-(K197-J197)),0)) | M197: =ROUND(I197-(K197-J197)-L197,2)
A198: 13 | B198: =F197 | C198: =IF(B198<=0.005,0,ROUND(B198*Inputs!$B$8,2)) | D198: =IF(B198<=0.005,0,MIN(Inputs!$B$7,B198+C198)) | E198: =IF(B198<=0.005,0,IF(A198=$B$4,MIN($B$3,B198-(D198-C198)),0)) | F198: =ROUND(B198-(D198-C198)-E198,2) | H198: 13 | I198: =M197 | J198: =IF(I198<=0.005,0,ROUND(I198*Inputs!$C$8,2)) | K198: =IF(I198<=0.005,0,MIN(Inputs!$C$7,I198+J198)) | L198: =IF(I198<=0.005,0,IF(H198=$B$4,MIN($B$3,I198-(K198-J198)),0)) | M198: =ROUND(I198-(K198-J198)-L198,2)
... A365: 180 | B365: =F364 | C365: =IF(B365<=0.005,0,ROUND(B365*Inputs!$B$8,2)) | D365: =IF(B365<=0.005,0,MIN(Inputs!$B$7,B365+C365)) | E365: =IF(B365<=0.005,0,IF(A365=$B$4,MIN($B$3,B365-(D365-C365)),0)) | F365: =ROUND(B365-(D365-C365)-E365,2) | H365: 180 | I365: =M364 | J365: =IF(I365<=0.005,0,ROUND(I365*Inputs!$C$8,2)) | K365: =IF(I365<=0.005,0,MIN(Inputs!$C$7,I365+J365)) | L365: =IF(I365<=0.005,0,IF(H365=$B$4,MIN($B$3,I365-(K365-J365)),0)) | M365: =ROUND(I365-(K365-J365)-L365,2)

Sheet HDFC Rules
A1: HDFC HOME-LOAN PREPAYMENT RULES (verified June 2026)
A3: Rule | B3: Value / note
A4: Prepayment charge (floating) | B4: NONE. RBI ban from 1 Jan 2026 on floating loans to individuals (non-business) — any amount, any source.
A5: Frequency | B5: Once per calendar month (up to 12x / year).
A6: Minimum part payment | B6: Rs 5,000 or 1 EMI, whichever is HIGHER.
A7: Maximum part payment | B7: Rs 50 lakh/month OR 75% of year-opening principal, whichever is LOWER.
A8: Timing | B8: Allowed only after 1 month of EMI commencement (not in month 1).
A9: Source of funds | B9: From the repayment-tagged bank account (or branch visit).
A10: Default after prepay | B10: Tenure reduction (EMI fixed, loan shortens) — used by this model.
A12: Sources: HDFC FAQ (homeloans.hdfc.bank.in/checklist/faqs), HDFC prepayment page, RBI 2026 directive. Note: 'Max' check uses the prepay-month opening balance as a proxy for year-opening principal.
